{
  "_id": "677261e4e240a7d43f0efae7",
  "title": "update tweet videos",
  "outputEntity": [
    "674e8ef485bc5241dd6405dd"
  ],
  "queryAdvance": "{\n  \"title\":0,\n  \"slug\":0,\n  \"short_description\":0,\n  \"video_link\":0,\n  \"video_file\":0,\n  \"featured_image\":0,\n  \"categories\":0,\n  \"tag\":0,\n  \"youtube_path\":0,\n  \"comment_off\":0,\n  \"like_off\":0,\n  \"status\":\"active,send_to_review,archive,reject\",\n  \"approve_at\":0,\n  \"approve_by\":0,\n  \"published_at\":0,\n  \"report_tweet_off\":0,\n  \"report_comment_off\":0\n}",
  "note": "",
  "method": "put",
  "locale": null,
  "locale_id": null,
  "tenant_id": "674028d2611a654e763a73e8",
  "documents": []
}