{
  "tweets-group-draft": {},
  "post": {
    "headers": [
      {
        "value": "user.id",
        "key": "user.id"
      }
    ],
    "params": [
      {
        "value": "group_id",
        "key": "group_id"
      },
      {
        "value": "_id",
        "key": "_id"
      }
    ],
    "body": [
      {
        "value": "social_group",
        "key": "social_group"
      }
    ],
    "validate": [
      {
        "notification": {},
        "response": {
          "_id": "67be997b7df148c72be0c5c7",
          "title": "Create tweet news with status draft",
          "entity": "mge-tweet-social-news",
          "path_file": "json/response/67be997b7df148c72be0c5c7.json"
        },
        "query_validate": {
          "combinator": "and",
          "rules": [
            {
              "id": "9138bbe3-eeca-471e-ab91-54ed32ff8655",
              "field": "data",
              "operator": "=",
              "valueSource": "value",
              "value": "675a8e9b0f44fc1769fdea90"
            },
            {
              "id": "14f70164-0767-4918-8926-4f4248e17966",
              "field": "data",
              "operator": "=",
              "valueSource": "value",
              "value": "674d2f9f4b5b2e5f92441d16"
            }
          ],
          "id": "f9237d21-b676-46f0-8e03-ed7479a8b6b0"
        },
        "list_validate": [
          {
            "_id": "675a8e9b0f44fc1769fdea90",
            "title": "is-user-active 1",
            "entity": {
              "_id": "6749933810905d9ddbd0104b",
              "mongodb_collection_name": "user"
            },
            "path_file": "json/validate/675a8e9b0f44fc1769fdea90.json"
          },
          {
            "_id": "674d2f9f4b5b2e5f92441d16",
            "title": "user-joined-group",
            "entity": {
              "_id": "674810a776462b61b5df8ece",
              "mongodb_collection_name": "mge-group-member"
            },
            "path_file": "json/validate/674d2f9f4b5b2e5f92441d16.json"
          }
        ],
        "custom_filter": {
          "id": "5d6a2016-dc1b-4783-a0f6-3fda29f2b197",
          "rules": [
            {
              "id": "f4f05d03-7f08-4bfa-bc6d-28f022f86458",
              "field": 0,
              "operator": "=",
              "valueSource": "value",
              "value": "news"
            }
          ],
          "combinator": "and",
          "not": false
        }
      },
      {
        "notification": {},
        "response": {
          "_id": "67be9a197df148c72be0c78a",
          "title": "Create tweet image with status draft",
          "entity": "mge-tweet-social-image",
          "path_file": "json/response/67be9a197df148c72be0c78a.json"
        },
        "query_validate": {
          "combinator": "and",
          "rules": [
            {
              "id": "9138bbe3-eeca-471e-ab91-54ed32ff8655",
              "field": "data",
              "operator": "=",
              "valueSource": "value",
              "value": "675a8e9b0f44fc1769fdea90"
            },
            {
              "id": "14f70164-0767-4918-8926-4f4248e17966",
              "field": "data",
              "operator": "=",
              "valueSource": "value",
              "value": "674d2f9f4b5b2e5f92441d16"
            }
          ],
          "id": "f9237d21-b676-46f0-8e03-ed7479a8b6b0"
        },
        "list_validate": [
          {
            "_id": "675a8e9b0f44fc1769fdea90",
            "title": "is-user-active 1",
            "entity": {
              "_id": "6749933810905d9ddbd0104b",
              "mongodb_collection_name": "user"
            },
            "path_file": "json/validate/675a8e9b0f44fc1769fdea90.json"
          },
          {
            "_id": "674d2f9f4b5b2e5f92441d16",
            "title": "user-joined-group",
            "entity": {
              "_id": "674810a776462b61b5df8ece",
              "mongodb_collection_name": "mge-group-member"
            },
            "path_file": "json/validate/674d2f9f4b5b2e5f92441d16.json"
          }
        ],
        "custom_filter": {
          "id": "585ce8db-4ec5-4cd0-8a4b-e7ed1cea7c99",
          "rules": [
            {
              "id": "5b05f94e-d1e8-4fec-a86d-b73627eda6e3",
              "field": 0,
              "operator": "=",
              "valueSource": "value",
              "value": "image"
            }
          ],
          "combinator": "and",
          "not": false
        }
      },
      {
        "notification": {},
        "response": {
          "_id": "67be99cd7df148c72be0c6e0",
          "title": "Create tweet videos with status draft",
          "entity": "mge-tweet-social-videos",
          "path_file": "json/response/67be99cd7df148c72be0c6e0.json"
        },
        "query_validate": {
          "combinator": "and",
          "rules": [
            {
              "id": "9138bbe3-eeca-471e-ab91-54ed32ff8655",
              "field": "data",
              "operator": "=",
              "valueSource": "value",
              "value": "675a8e9b0f44fc1769fdea90"
            },
            {
              "id": "14f70164-0767-4918-8926-4f4248e17966",
              "field": "data",
              "operator": "=",
              "valueSource": "value",
              "value": "674d2f9f4b5b2e5f92441d16"
            }
          ],
          "id": "f9237d21-b676-46f0-8e03-ed7479a8b6b0"
        },
        "list_validate": [
          {
            "_id": "675a8e9b0f44fc1769fdea90",
            "title": "is-user-active 1",
            "entity": {
              "_id": "6749933810905d9ddbd0104b",
              "mongodb_collection_name": "user"
            },
            "path_file": "json/validate/675a8e9b0f44fc1769fdea90.json"
          },
          {
            "_id": "674d2f9f4b5b2e5f92441d16",
            "title": "user-joined-group",
            "entity": {
              "_id": "674810a776462b61b5df8ece",
              "mongodb_collection_name": "mge-group-member"
            },
            "path_file": "json/validate/674d2f9f4b5b2e5f92441d16.json"
          }
        ],
        "custom_filter": {
          "id": "54982466-7e9d-4df8-9282-b4cd6075cc01",
          "rules": [
            {
              "id": "a6bb0072-cb94-4b9a-93b8-85b16eb82d62",
              "field": 0,
              "operator": "=",
              "valueSource": "value",
              "value": "videos"
            }
          ],
          "combinator": "and",
          "not": false
        }
      },
      {
        "notification": {},
        "response": {
          "_id": "67be9aab7df148c72be0c9ee",
          "title": "Create tweet votes with status draft",
          "entity": "mge-tweet-social-votes",
          "path_file": "json/response/67be9aab7df148c72be0c9ee.json"
        },
        "query_validate": {
          "combinator": "and",
          "rules": [
            {
              "id": "9138bbe3-eeca-471e-ab91-54ed32ff8655",
              "field": "data",
              "operator": "=",
              "valueSource": "value",
              "value": "675a8e9b0f44fc1769fdea90"
            },
            {
              "id": "14f70164-0767-4918-8926-4f4248e17966",
              "field": "data",
              "operator": "=",
              "valueSource": "value",
              "value": "674d2f9f4b5b2e5f92441d16"
            }
          ],
          "id": "f9237d21-b676-46f0-8e03-ed7479a8b6b0"
        },
        "list_validate": [
          {
            "_id": "675a8e9b0f44fc1769fdea90",
            "title": "is-user-active 1",
            "entity": {
              "_id": "6749933810905d9ddbd0104b",
              "mongodb_collection_name": "user"
            },
            "path_file": "json/validate/675a8e9b0f44fc1769fdea90.json"
          },
          {
            "_id": "674d2f9f4b5b2e5f92441d16",
            "title": "user-joined-group",
            "entity": {
              "_id": "674810a776462b61b5df8ece",
              "mongodb_collection_name": "mge-group-member"
            },
            "path_file": "json/validate/674d2f9f4b5b2e5f92441d16.json"
          }
        ],
        "custom_filter": {
          "id": "9bb55409-e5ad-4c9d-8276-5d5791b8a813",
          "rules": [
            {
              "id": "f65669c0-d440-43f1-93a7-f7afd26635b0",
              "field": 0,
              "operator": "=",
              "valueSource": "value",
              "value": "votes"
            }
          ],
          "combinator": "and",
          "not": false
        }
      },
      {
        "notification": {},
        "response": {
          "_id": "68873169edb2b79b9533af76",
          "title": "create tweet file with status draft",
          "entity": "mge-tweet-social-file",
          "path_file": "json/response/68873169edb2b79b9533af76.json"
        },
        "query_validate": {
          "combinator": "and",
          "rules": [
            {
              "id": "9138bbe3-eeca-471e-ab91-54ed32ff8655",
              "field": "data",
              "operator": "=",
              "valueSource": "value",
              "value": "675a8e9b0f44fc1769fdea90"
            },
            {
              "id": "14f70164-0767-4918-8926-4f4248e17966",
              "field": "data",
              "operator": "=",
              "valueSource": "value",
              "value": "674d2f9f4b5b2e5f92441d16"
            }
          ],
          "id": "f9237d21-b676-46f0-8e03-ed7479a8b6b0"
        },
        "list_validate": [
          {
            "_id": "675a8e9b0f44fc1769fdea90",
            "title": "is-user-active 1",
            "entity": {
              "_id": "6749933810905d9ddbd0104b",
              "mongodb_collection_name": "user"
            },
            "path_file": "json/validate/675a8e9b0f44fc1769fdea90.json"
          },
          {
            "_id": "674d2f9f4b5b2e5f92441d16",
            "title": "user-joined-group",
            "entity": {
              "_id": "674810a776462b61b5df8ece",
              "mongodb_collection_name": "mge-group-member"
            },
            "path_file": "json/validate/674d2f9f4b5b2e5f92441d16.json"
          }
        ],
        "custom_filter": {
          "id": "11d05a7c-a082-47a7-8c91-94e31ac4800f",
          "rules": [
            {
              "id": "cc942a44-4e8e-4bee-84e0-c6f44f364e2a",
              "field": 0,
              "operator": "=",
              "valueSource": "value",
              "value": "file"
            }
          ],
          "combinator": "and",
          "not": false
        }
      },
      {
        "notification": {},
        "response": {
          "_id": "688731c2edb2b79b9533af91",
          "title": "create tweet event with status draft",
          "entity": "mge-tweet-social-event",
          "path_file": "json/response/688731c2edb2b79b9533af91.json"
        },
        "query_validate": {
          "combinator": "and",
          "rules": [
            {
              "id": "9138bbe3-eeca-471e-ab91-54ed32ff8655",
              "field": "data",
              "operator": "=",
              "valueSource": "value",
              "value": "675a8e9b0f44fc1769fdea90"
            },
            {
              "id": "14f70164-0767-4918-8926-4f4248e17966",
              "field": "data",
              "operator": "=",
              "valueSource": "value",
              "value": "674d2f9f4b5b2e5f92441d16"
            }
          ],
          "id": "f9237d21-b676-46f0-8e03-ed7479a8b6b0"
        },
        "list_validate": [
          {
            "_id": "675a8e9b0f44fc1769fdea90",
            "title": "is-user-active 1",
            "entity": {
              "_id": "6749933810905d9ddbd0104b",
              "mongodb_collection_name": "user"
            },
            "path_file": "json/validate/675a8e9b0f44fc1769fdea90.json"
          },
          {
            "_id": "674d2f9f4b5b2e5f92441d16",
            "title": "user-joined-group",
            "entity": {
              "_id": "674810a776462b61b5df8ece",
              "mongodb_collection_name": "mge-group-member"
            },
            "path_file": "json/validate/674d2f9f4b5b2e5f92441d16.json"
          }
        ],
        "custom_filter": {
          "id": "efc8271b-80a6-4d91-9ac3-cce0c3e34801",
          "rules": [
            {
              "id": "9ce39da9-17b7-4adf-8c3f-ce2e70492ce1",
              "field": 0,
              "operator": "=",
              "valueSource": "value",
              "value": "event"
            }
          ],
          "combinator": "and",
          "not": false
        }
      }
    ]
  },
  "put": {
    "headers": [],
    "params": [],
    "body": [],
    "validate": [
      {
        "notification": {},
        "response": {
          "_id": "68873af4edb2b79b9533b5ab",
          "title": "update tweet new with status draft",
          "entity": "mge-tweet-social-news",
          "path_file": "json/response/68873af4edb2b79b9533b5ab.json"
        },
        "query_validate": {
          "combinator": "and",
          "rules": [
            {
              "id": "ba418d5a-93ce-4e59-bd00-5e67359cf820",
              "field": "data",
              "operator": "=",
              "valueSource": "value",
              "value": "675a8e9b0f44fc1769fdea90"
            },
            {
              "id": "50435f5b-6731-4cbb-b687-213b25863d72",
              "field": "data",
              "operator": "=",
              "valueSource": "value",
              "value": "67f8f04d36ac50fe5604e71e"
            },
            {
              "id": "b70d4dc2-b39b-4181-bc66-59af3f167a73",
              "field": "data",
              "operator": "=",
              "valueSource": "value",
              "value": "6772c07401dfc8643f077e14"
            }
          ],
          "id": "c96c4a83-6de9-4685-b1af-9f6726ac631f"
        },
        "list_validate": [
          {
            "_id": "675a8e9b0f44fc1769fdea90",
            "title": "is-user-active-in-tenant",
            "entity": {
              "_id": "67aad740a67aaa1951ca64b0",
              "mongodb_collection_name": "user-tenant-profile"
            },
            "path_file": "json/validate/675a8e9b0f44fc1769fdea90.json"
          },
          {
            "_id": "67f8f04d36ac50fe5604e71e",
            "title": "is-user-joined-group",
            "entity": {},
            "path_file": "json/validate/67f8f04d36ac50fe5604e71e.json"
          },
          {
            "_id": "6772c07401dfc8643f077e14",
            "title": "is-the-author-of-tweet",
            "entity": {
              "_id": "6747ef07c47463d88f8c5ab1",
              "mongodb_collection_name": "mge-group"
            },
            "path_file": "json/validate/6772c07401dfc8643f077e14.json"
          }
        ],
        "custom_filter": {
          "id": "7adcadb1-20ba-4722-8f54-ac28ddd7bd9f",
          "rules": [
            {
              "id": "4d37beef-a0ff-43a8-aa7c-d1a027546323",
              "field": 0,
              "operator": "=",
              "valueSource": "value",
              "value": "news"
            }
          ],
          "combinator": "and",
          "not": false
        }
      },
      {
        "notification": {},
        "response": {
          "_id": "68873b9fedb2b79b9533b631",
          "title": "update tweet image with status draft",
          "entity": "mge-tweet-social-image",
          "path_file": "json/response/68873b9fedb2b79b9533b631.json"
        },
        "query_validate": {
          "combinator": "and",
          "rules": [
            {
              "id": "ba418d5a-93ce-4e59-bd00-5e67359cf820",
              "field": "data",
              "operator": "=",
              "valueSource": "value",
              "value": "675a8e9b0f44fc1769fdea90"
            },
            {
              "id": "50435f5b-6731-4cbb-b687-213b25863d72",
              "field": "data",
              "operator": "=",
              "valueSource": "value",
              "value": "67f8f04d36ac50fe5604e71e"
            },
            {
              "id": "b70d4dc2-b39b-4181-bc66-59af3f167a73",
              "field": "data",
              "operator": "=",
              "valueSource": "value",
              "value": "6772c07401dfc8643f077e14"
            }
          ],
          "id": "c96c4a83-6de9-4685-b1af-9f6726ac631f"
        },
        "list_validate": [
          {
            "_id": "675a8e9b0f44fc1769fdea90",
            "title": "is-user-active-in-tenant",
            "entity": {
              "_id": "67aad740a67aaa1951ca64b0",
              "mongodb_collection_name": "user-tenant-profile"
            },
            "path_file": "json/validate/675a8e9b0f44fc1769fdea90.json"
          },
          {
            "_id": "67f8f04d36ac50fe5604e71e",
            "title": "is-user-joined-group",
            "entity": {},
            "path_file": "json/validate/67f8f04d36ac50fe5604e71e.json"
          },
          {
            "_id": "6772c07401dfc8643f077e14",
            "title": "is-the-author-of-tweet",
            "entity": {
              "_id": "6747ef07c47463d88f8c5ab1",
              "mongodb_collection_name": "mge-group"
            },
            "path_file": "json/validate/6772c07401dfc8643f077e14.json"
          }
        ],
        "custom_filter": {
          "id": "0bf10a96-cc12-4053-b994-ceb2b0d19836",
          "rules": [
            {
              "id": "892ffb30-0f20-4d92-a925-8f748d31e2d1",
              "field": 0,
              "operator": "=",
              "valueSource": "value",
              "value": "image"
            }
          ],
          "combinator": "and",
          "not": false
        }
      },
      {
        "notification": {},
        "response": {
          "_id": "68873c03edb2b79b9533b6e8",
          "title": "update tweet video with status draft",
          "entity": "mge-tweet-social-videos",
          "path_file": "json/response/68873c03edb2b79b9533b6e8.json"
        },
        "query_validate": {
          "combinator": "and",
          "rules": [
            {
              "id": "ba418d5a-93ce-4e59-bd00-5e67359cf820",
              "field": "data",
              "operator": "=",
              "valueSource": "value",
              "value": "675a8e9b0f44fc1769fdea90"
            },
            {
              "id": "50435f5b-6731-4cbb-b687-213b25863d72",
              "field": "data",
              "operator": "=",
              "valueSource": "value",
              "value": "67f8f04d36ac50fe5604e71e"
            },
            {
              "id": "b70d4dc2-b39b-4181-bc66-59af3f167a73",
              "field": "data",
              "operator": "=",
              "valueSource": "value",
              "value": "6772c07401dfc8643f077e14"
            }
          ],
          "id": "c96c4a83-6de9-4685-b1af-9f6726ac631f"
        },
        "list_validate": [
          {
            "_id": "675a8e9b0f44fc1769fdea90",
            "title": "is-user-active-in-tenant",
            "entity": {
              "_id": "67aad740a67aaa1951ca64b0",
              "mongodb_collection_name": "user-tenant-profile"
            },
            "path_file": "json/validate/675a8e9b0f44fc1769fdea90.json"
          },
          {
            "_id": "67f8f04d36ac50fe5604e71e",
            "title": "is-user-joined-group",
            "entity": {},
            "path_file": "json/validate/67f8f04d36ac50fe5604e71e.json"
          },
          {
            "_id": "6772c07401dfc8643f077e14",
            "title": "is-the-author-of-tweet",
            "entity": {
              "_id": "6747ef07c47463d88f8c5ab1",
              "mongodb_collection_name": "mge-group"
            },
            "path_file": "json/validate/6772c07401dfc8643f077e14.json"
          }
        ],
        "custom_filter": {
          "id": "92822af3-09e3-4aed-b347-eef6b31cbb68",
          "rules": [
            {
              "id": "a441f4d0-7a26-4fac-8966-6188e2ff7cbe",
              "field": 0,
              "operator": "=",
              "valueSource": "value",
              "value": "videos"
            }
          ],
          "combinator": "and",
          "not": false
        }
      },
      {
        "notification": {},
        "response": {
          "_id": "68873c47edb2b79b9533b70b",
          "title": "update tweet vote with status draft",
          "entity": "mge-tweet-social-votes",
          "path_file": "json/response/68873c47edb2b79b9533b70b.json"
        },
        "query_validate": {
          "combinator": "and",
          "rules": [
            {
              "id": "ba418d5a-93ce-4e59-bd00-5e67359cf820",
              "field": "data",
              "operator": "=",
              "valueSource": "value",
              "value": "675a8e9b0f44fc1769fdea90"
            },
            {
              "id": "50435f5b-6731-4cbb-b687-213b25863d72",
              "field": "data",
              "operator": "=",
              "valueSource": "value",
              "value": "67f8f04d36ac50fe5604e71e"
            },
            {
              "id": "b70d4dc2-b39b-4181-bc66-59af3f167a73",
              "field": "data",
              "operator": "=",
              "valueSource": "value",
              "value": "6772c07401dfc8643f077e14"
            }
          ],
          "id": "c96c4a83-6de9-4685-b1af-9f6726ac631f"
        },
        "list_validate": [
          {
            "_id": "675a8e9b0f44fc1769fdea90",
            "title": "is-user-active-in-tenant",
            "entity": {
              "_id": "67aad740a67aaa1951ca64b0",
              "mongodb_collection_name": "user-tenant-profile"
            },
            "path_file": "json/validate/675a8e9b0f44fc1769fdea90.json"
          },
          {
            "_id": "67f8f04d36ac50fe5604e71e",
            "title": "is-user-joined-group",
            "entity": {},
            "path_file": "json/validate/67f8f04d36ac50fe5604e71e.json"
          },
          {
            "_id": "6772c07401dfc8643f077e14",
            "title": "is-the-author-of-tweet",
            "entity": {
              "_id": "6747ef07c47463d88f8c5ab1",
              "mongodb_collection_name": "mge-group"
            },
            "path_file": "json/validate/6772c07401dfc8643f077e14.json"
          }
        ],
        "custom_filter": {
          "id": "2705bae0-b2e5-4971-9952-88a05192c692",
          "rules": [
            {
              "id": "e640f7da-82fd-4d67-a625-fb30327790a5",
              "field": 0,
              "operator": "=",
              "valueSource": "value",
              "value": "votes"
            }
          ],
          "combinator": "and",
          "not": false
        }
      },
      {
        "notification": {},
        "response": {
          "_id": "68873c7cedb2b79b9533b715",
          "title": "update tweet file with status draft",
          "entity": "mge-tweet-social-file",
          "path_file": "json/response/68873c7cedb2b79b9533b715.json"
        },
        "query_validate": {
          "combinator": "and",
          "rules": [
            {
              "id": "ba418d5a-93ce-4e59-bd00-5e67359cf820",
              "field": "data",
              "operator": "=",
              "valueSource": "value",
              "value": "675a8e9b0f44fc1769fdea90"
            },
            {
              "id": "50435f5b-6731-4cbb-b687-213b25863d72",
              "field": "data",
              "operator": "=",
              "valueSource": "value",
              "value": "67f8f04d36ac50fe5604e71e"
            },
            {
              "id": "b70d4dc2-b39b-4181-bc66-59af3f167a73",
              "field": "data",
              "operator": "=",
              "valueSource": "value",
              "value": "6772c07401dfc8643f077e14"
            }
          ],
          "id": "c96c4a83-6de9-4685-b1af-9f6726ac631f"
        },
        "list_validate": [
          {
            "_id": "675a8e9b0f44fc1769fdea90",
            "title": "is-user-active-in-tenant",
            "entity": {
              "_id": "67aad740a67aaa1951ca64b0",
              "mongodb_collection_name": "user-tenant-profile"
            },
            "path_file": "json/validate/675a8e9b0f44fc1769fdea90.json"
          },
          {
            "_id": "67f8f04d36ac50fe5604e71e",
            "title": "is-user-joined-group",
            "entity": {},
            "path_file": "json/validate/67f8f04d36ac50fe5604e71e.json"
          },
          {
            "_id": "6772c07401dfc8643f077e14",
            "title": "is-the-author-of-tweet",
            "entity": {
              "_id": "6747ef07c47463d88f8c5ab1",
              "mongodb_collection_name": "mge-group"
            },
            "path_file": "json/validate/6772c07401dfc8643f077e14.json"
          }
        ],
        "custom_filter": {
          "id": "c21bba5c-76f2-48bc-91c5-673def2b24cc",
          "rules": [
            {
              "id": "2dbd68ff-2972-4a7f-a5d7-ac617bc21cc2",
              "field": 0,
              "operator": "=",
              "valueSource": "value",
              "value": "file"
            }
          ],
          "combinator": "and",
          "not": false
        }
      },
      {
        "notification": {},
        "response": {
          "_id": "68873cf2edb2b79b9533b74b",
          "title": "update tweet event with status draft",
          "entity": "mge-tweet-social-event",
          "path_file": "json/response/68873cf2edb2b79b9533b74b.json"
        },
        "query_validate": {
          "combinator": "and",
          "rules": [
            {
              "id": "ba418d5a-93ce-4e59-bd00-5e67359cf820",
              "field": "data",
              "operator": "=",
              "valueSource": "value",
              "value": "675a8e9b0f44fc1769fdea90"
            },
            {
              "id": "50435f5b-6731-4cbb-b687-213b25863d72",
              "field": "data",
              "operator": "=",
              "valueSource": "value",
              "value": "67f8f04d36ac50fe5604e71e"
            },
            {
              "id": "b70d4dc2-b39b-4181-bc66-59af3f167a73",
              "field": "data",
              "operator": "=",
              "valueSource": "value",
              "value": "6772c07401dfc8643f077e14"
            }
          ],
          "id": "c96c4a83-6de9-4685-b1af-9f6726ac631f"
        },
        "list_validate": [
          {
            "_id": "675a8e9b0f44fc1769fdea90",
            "title": "is-user-active-in-tenant",
            "entity": {
              "_id": "67aad740a67aaa1951ca64b0",
              "mongodb_collection_name": "user-tenant-profile"
            },
            "path_file": "json/validate/675a8e9b0f44fc1769fdea90.json"
          },
          {
            "_id": "67f8f04d36ac50fe5604e71e",
            "title": "is-user-joined-group",
            "entity": {},
            "path_file": "json/validate/67f8f04d36ac50fe5604e71e.json"
          },
          {
            "_id": "6772c07401dfc8643f077e14",
            "title": "is-the-author-of-tweet",
            "entity": {
              "_id": "6747ef07c47463d88f8c5ab1",
              "mongodb_collection_name": "mge-group"
            },
            "path_file": "json/validate/6772c07401dfc8643f077e14.json"
          }
        ],
        "custom_filter": {
          "id": "7c514c35-fa59-4f66-b62c-394876581cf8",
          "rules": [
            {
              "id": "d55dda06-e9d9-495d-a10c-9d6a63eabf2e",
              "field": 0,
              "operator": "=",
              "valueSource": "value",
              "value": "event"
            }
          ],
          "combinator": "and",
          "not": false
        }
      }
    ]
  }
}